myriambizart_picsou/__init__.py
myriambizart_picsou/picsou.py
myriambizart_picsou-0.1.0.dist-info/METADATA
myriambizart_picsou-0.1.0.dist-info/WHEEL
myriambizart_picsou-0.1.0.dist-info/RECORD
